<?xml version="1.0" encoding="utf-8"?>
<LanguageData>
  <!--The following translations were generated by https://www.deepl.com/-->
  <!-- EN: Artillery -->
  <RWP_Artillery.label>Artillerie</RWP_Artillery.label>
  <!-- EN: Unlocks the ability to manufacture the 12-pounder Napoleon cannon and the 12-pound Coehorn mortar. -->
  <RWP_Artillery.description>Débloque la possibilité de fabriquer le canon Napoléon de 12 livres et le mortier Coehorn de 12 livres.</RWP_Artillery.description>
  <!-- EN: Gatling Gun -->
  <RWP_GatlingGun.label>Gatling Gun</RWP_GatlingGun.label>
  <!-- EN: Unlocks the ability to manufacture the Model 1881 Gatling gun. -->
  <RWP_GatlingGun.description>Débloque la capacité de fabriquer la mitrailleuse Gatling modèle 1881.</RWP_GatlingGun.description>
  <!-- EN: law enforcement -->
  <RWP_LawEnforcement.label>application de la loi</RWP_LawEnforcement.label>
  <!-- EN: Unlocks the ability to manufacture and issue town law enforcement badges. -->
  <RWP_LawEnforcement.description>Débloque la possibilité de fabriquer et d'émettre des badges pour les forces de l'ordre de la ville.</RWP_LawEnforcement.description>
  <!-- EN: Basic optometry -->
  <RWP_Optometry.label>L'optométrie de base</RWP_Optometry.label>
  <!-- EN: Unlocks the ability to manufacture spectacles. -->
  <RWP_Optometry.description>Débloque la capacité de fabriquer des lunettes.</RWP_Optometry.description>
  <!-- EN: watchmaking -->
  <RWP_Watchmaking.label>horlogerie</RWP_Watchmaking.label>
  <!-- EN: Unlocks the ability to manufacture pocketwatches. -->
  <RWP_Watchmaking.description>Débloque la possibilité de fabriquer des montres de poche.</RWP_Watchmaking.description>
  <!-- EN: Old West apparel -->
  <RWP_WesternApparel.label>Vêtements de l'Ouest</RWP_WesternApparel.label>
  <!-- EN: Unlocks the ability to manufacture various advanced western apparel. -->
  <RWP_WesternApparel.description>Débloque la capacité de fabriquer divers vêtements occidentaux avancés.</RWP_WesternApparel.description>
</LanguageData>
